Metadata-Version: 2.1
Name: cyberfly-data-shipper
Version: 0.2.1
Home-page: https://github.com/cyberfly-io/data-shipper
